photomatrix/__init__.py
photomatrix/__main__.py
photomatrix/arguments.py
photomatrix/exif.py
photomatrix/finalize.py
photomatrix/matrix.py
photomatrix/preprocess.py
photomatrix/text.py
photomatrix-0.0.5.dist-info/LICENSE
photomatrix-0.0.5.dist-info/METADATA
photomatrix-0.0.5.dist-info/WHEEL
photomatrix-0.0.5.dist-info/entry_points.txt
photomatrix-0.0.5.dist-info/top_level.txt
photomatrix-0.0.5.dist-info/RECORD
