Metadata-Version: 2.1
Name: photomatrix
Version: 0.0.5
Summary: Concat photos together in a matrix
Home-page: https://github.com/ffeltrinelli/photomatrix
Author: Francesco Feltrinelli
License: UNKNOWN
Platform: UNKNOWN
Classifier: Programming Language :: Python :: 3.7
Classifier: License :: OSI Approved :: Apache Software License
Classifier: Operating System :: OS Independent
Classifier: Development Status :: 3 - Alpha
Requires-Python: >=3.7
Requires-Dist: pillow (>=7)
Requires-Dist: fonts
Requires-Dist: font-source-sans-pro
Requires-Dist: importlib-metadata (~=1.0) ; python_version < "3.8"
